[
  {
   "pins": [
      [
        "VGND",
        "VPWR"
      ], [
        "VGND",
        "VPWR"
      ]
   ]
  },
  {
   "pins": [
      [
        "VPWR",
        "VGND",
        "VPB",
        "VNB"
      ], [
        "VPWR",
        "VGND",
        "VPB",
        "VNB"
      ]
   ]
  },
  {
   "pins": [
      [
        "VGND",
        "VNB",
        "VPB",
        "VPWR"
      ], [
        "VGND",
        "VNB",
        "VPB",
        "VPWR"
      ]
   ]
  },
  {
   "pins": [
      [
        "VGND",
        "VNB",
        "VPB",
        "VPWR"
      ], [
        "VGND",
        "VNB",
        "VPB",
        "VPWR"
      ]
   ]
  },
  {
   "pins": [
      [
        "VGND",
        "VNB",
        "VPB",
        "VPWR"
      ], [
        "VGND",
        "VNB",
        "VPB",
        "VPWR"
      ]
   ]
  },
  {
   "pins": [
      [
        "A",
        "VGND",
        "VNB",
        "VPB",
        "VPWR",
        "X"
      ], [
        "A",
        "VGND",
        "VNB",
        "VPB",
        "VPWR",
        "X"
      ]
   ]
  },
  {
   "pins": [
      [
        "VGND",
        "VNB",
        "VPB",
        "VPWR"
      ], [
        "VGND",
        "VNB",
        "VPB",
        "VPWR"
      ]
   ]
  },
  {
   "pins": [
      [
        "VGND",
        "VNB",
        "VPB",
        "VPWR"
      ], [
        "VGND",
        "VNB",
        "VPB",
        "VPWR"
      ]
   ]
  },
  {
   "pins": [
      [
        "VGND",
        "VNB",
        "VPB",
        "VPWR"
      ], [
        "VGND",
        "VNB",
        "VPB",
        "VPWR"
      ]
   ]
  },
  {
   "pins": [
      [
        "A",
        "VGND",
        "VNB",
        "VPB",
        "VPWR",
        "X"
      ], [
        "A",
        "VGND",
        "VNB",
        "VPB",
        "VPWR",
        "X"
      ]
   ]
  },
  {
   "pins": [
      [
        "A1",
        "A2",
        "B1",
        "VGND",
        "VNB",
        "VPB",
        "VPWR",
        "X"
      ], [
        "A1",
        "A2",
        "B1",
        "VGND",
        "VNB",
        "VPB",
        "VPWR",
        "X"
      ]
   ]
  },
  {
   "pins": [
      [
        "A1",
        "A2",
        "B1_N",
        "VGND",
        "VNB",
        "VPB",
        "VPWR",
        "X"
      ], [
        "A1",
        "A2",
        "B1_N",
        "VGND",
        "VNB",
        "VPB",
        "VPWR",
        "X"
      ]
   ]
  },
  {
   "pins": [
      [
        "A",
        "B",
        "C_N",
        "VGND",
        "VNB",
        "VPB",
        "VPWR",
        "X"
      ], [
        "A",
        "B",
        "C_N",
        "VGND",
        "VNB",
        "VPB",
        "VPWR",
        "X"
      ]
   ]
  },
  {
   "pins": [
      [
        "A_N",
        "B",
        "C",
        "VGND",
        "VNB",
        "VPB",
        "VPWR",
        "X"
      ], [
        "A_N",
        "B",
        "C",
        "VGND",
        "VNB",
        "VPB",
        "VPWR",
        "X"
      ]
   ]
  },
  {
   "pins": [
      [
        "A0",
        "A1",
        "S",
        "VGND",
        "VNB",
        "VPB",
        "VPWR",
        "X"
      ], [
        "A0",
        "A1",
        "S",
        "VGND",
        "VNB",
        "VPB",
        "VPWR",
        "X"
      ]
   ]
  },
  {
   "pins": [
      [
        "A",
        "VGND",
        "VNB",
        "VPB",
        "VPWR",
        "X"
      ], [
        "A",
        "VGND",
        "VNB",
        "VPB",
        "VPWR",
        "X"
      ]
   ]
  },
  {
   "pins": [
      [
        "A",
        "VGND",
        "VNB",
        "VPB",
        "VPWR",
        "X"
      ], [
        "A",
        "VGND",
        "VNB",
        "VPB",
        "VPWR",
        "X"
      ]
   ]
  },
  {
   "pins": [
      [
        "A_N",
        "B",
        "VGND",
        "VNB",
        "VPB",
        "VPWR",
        "Y"
      ], [
        "A_N",
        "B",
        "VGND",
        "VNB",
        "VPB",
        "VPWR",
        "Y"
      ]
   ]
  },
  {
   "pins": [
      [
        "A",
        "B",
        "C_N",
        "VGND",
        "VNB",
        "VPB",
        "VPWR",
        "Y"
      ], [
        "A",
        "B",
        "C_N",
        "VGND",
        "VNB",
        "VPB",
        "VPWR",
        "Y"
      ]
   ]
  },
  {
   "name": [
      "Sign_Extender",
      "Sign_Extender"
   ],
   "devices": [
       [
         ["sky130_fd_sc_hd__tapvpwrvgnd_1", 1],
         ["sky130_ef_sc_hd__decap_12", 1],
         ["sky130_fd_sc_hd__fill_1", 1],
         ["sky130_fd_sc_hd__decap_3", 1],
         ["sky130_fd_sc_hd__fill_2", 1],
         ["sky130_fd_sc_hd__buf_2", 18],
         ["sky130_fd_sc_hd__decap_6", 1],
         ["sky130_fd_sc_hd__decap_4", 1],
         ["sky130_fd_sc_hd__decap_8", 1],
         ["sky130_fd_sc_hd__clkbuf_1", 9],
         ["sky130_fd_sc_hd__a21o_1", 6],
         ["sky130_fd_sc_hd__a21bo_1", 2],
         ["sky130_fd_sc_hd__or3b_1", 2],
         ["sky130_fd_sc_hd__and3b_1", 2],
         ["sky130_fd_sc_hd__mux2_1", 7],
         ["sky130_fd_sc_hd__buf_1", 4],
         ["sky130_fd_sc_hd__clkbuf_2", 1],
         ["sky130_fd_sc_hd__nand2b_4", 1],
         ["sky130_fd_sc_hd__nor3b_1", 1 ]
       ], [
         ["sky130_fd_sc_hd__tapvpwrvgnd_1", 1 ],
         ["sky130_ef_sc_hd__decap_12", 1 ],
         ["sky130_fd_sc_hd__fill_1", 1 ],
         ["sky130_fd_sc_hd__decap_3", 1 ],
         ["sky130_fd_sc_hd__fill_2", 1 ],
         ["sky130_fd_sc_hd__buf_2", 18 ],
         ["sky130_fd_sc_hd__decap_6", 1 ],
         ["sky130_fd_sc_hd__decap_4", 1 ],
         ["sky130_fd_sc_hd__decap_8", 1 ],
         ["sky130_fd_sc_hd__clkbuf_1", 9 ],
         ["sky130_fd_sc_hd__a21o_1", 6 ],
         ["sky130_fd_sc_hd__a21bo_1", 2 ],
         ["sky130_fd_sc_hd__or3b_1", 2 ],
         ["sky130_fd_sc_hd__and3b_1", 2 ],
         ["sky130_fd_sc_hd__mux2_1", 7 ],
         ["sky130_fd_sc_hd__buf_1", 4 ],
         ["sky130_fd_sc_hd__clkbuf_2", 1 ],
         ["sky130_fd_sc_hd__nand2b_4", 1 ],
         ["sky130_fd_sc_hd__nor3b_1", 1 ]
       ]
   ],
   "nets": [
    67,
    67
   ],
   "badnets": [
   ],
   "badelements": [
   ],
   "pins": [
      [
        "ImmSrc[1]",
        "instr[14]",
        "instr[13]",
        "ImmSrc[0]",
        "instr[6]",
        "instr[8]",
        "instr[7]",
        "instr[15]",
        "instr[12]",
        "instr[11]",
        "instr[9]",
        "instr[10]",
        "ImmExt[15]",
        "ImmExt[13]",
        "ImmExt[14]",
        "ImmExt[8]",
        "ImmExt[7]",
        "ImmExt[6]",
        "ImmExt[12]",
        "ImmExt[11]",
        "ImmExt[10]",
        "ImmExt[9]",
        "ImmExt[5]",
        "ImmExt[4]",
        "ImmExt[3]",
        "ImmExt[2]",
        "ImmExt[0]",
        "ImmExt[1]",
        "VGND",
        "VPWR",
        "instr[0]",
        "instr[1]",
        "instr[2]",
        "instr[3]",
        "instr[4]",
        "instr[5]"
      ], [
        "ImmSrc[1]",
        "instr[14]",
        "instr[13]",
        "ImmSrc[0]",
        "instr[6]",
        "instr[8]",
        "instr[7]",
        "instr[15]",
        "instr[12]",
        "instr[11]",
        "instr[9]",
        "instr[10]",
        "ImmExt[15]",
        "ImmExt[13]",
        "ImmExt[14]",
        "ImmExt[8]",
        "ImmExt[7]",
        "ImmExt[6]",
        "ImmExt[12]",
        "ImmExt[11]",
        "ImmExt[10]",
        "ImmExt[9]",
        "ImmExt[5]",
        "ImmExt[4]",
        "ImmExt[3]",
        "ImmExt[2]",
        "ImmExt[0]",
        "ImmExt[1]",
        "VGND",
        "VPWR",
        "instr[0]",
        "instr[1]",
        "instr[2]",
        "instr[3]",
        "instr[4]",
        "instr[5]"
      ]
   ]
  }
]
